savanty/__init__.py
savanty/cli.py
savanty/dspy_modules.py
savanty/solver.py
savanty/templates/index.html
savanty-0.2.1.dist-info/LICENSE
savanty-0.2.1.dist-info/METADATA
savanty-0.2.1.dist-info/WHEEL
savanty-0.2.1.dist-info/entry_points.txt
savanty-0.2.1.dist-info/RECORD
