Metadata-Version: 2.3
Name: savanty
Version: 0.2.1
Summary: An intelligent optimization problem solver using LLMs and Answer Set Programming
License: MIT
Keywords: optimization,llm,asp,clingo,clorm,ai
Author: Dipankar Sarkar
Author-email: me@dipankar.name
Requires-Python: >=3.10,<3.14
Classifier: Development Status :: 3 - Alpha
Classifier: Intended Audience :: Developers
Classifier: Intended Audience :: Science/Research
Classifier: License :: OSI Approved :: MIT License
Classifier: Programming Language :: Python :: 3
Classifier: Programming Language :: Python :: 3.10
Classifier: Programming Language :: Python :: 3.11
Classifier: Programming Language :: Python :: 3.12
Classifier: Programming Language :: Python :: 3.13
Classifier: Programming Language :: Python :: 3.8
Classifier: Programming Language :: Python :: 3.9
Classifier: Topic :: Scientific/Engineering :: Artificial Intelligence
Classifier: Topic :: Software Development :: Libraries :: Python Modules
Requires-Dist: click (>=8.0.0,<9.0.0)
Requires-Dist: clorm (>=1.6.0,<2.0.0)
Requires-Dist: dspy-ai (>=3.0.0,<4.0.0)
Requires-Dist: fastapi (>=0.115.12,<0.116.0)
Requires-Dist: fastmcp (>=2.0.0,<3.0.0)
Requires-Dist: openai (>=1.0.0,<2.0.0)
Requires-Dist: uvicorn (>=0.31.1,<0.32.0)
Project-URL: Repository, https://github.com/skelf-research/savanty
